onweb/__init__.py
onweb/__main__.py
onweb-0.6.0.dist-info/LICENSE.txt
onweb-0.6.0.dist-info/METADATA
onweb-0.6.0.dist-info/WHEEL
onweb-0.6.0.dist-info/entry_points.txt
onweb-0.6.0.dist-info/top_level.txt
onweb-0.6.0.dist-info/RECORD
