Metadata-Version: 2.1
Name: onweb
Version: 0.6.0
Summary: Check the status of some website.
Home-page: https://github.com/fmind/onweb
Author: Médéric Hurier (fmind)
Author-email: fmind@fmind.me
License: LGPL-3.0
Keywords: check status website
Platform: UNKNOWN
Classifier: Development Status :: 4 - Beta
Requires-Python: >=3.7
Requires-Dist: aiohttp
